bioacoustics_augmentation/__init__.py
bioacoustics_augmentation/_modidx.py
bioacoustics_augmentation/core.py
bioacoustics_augmentation/augmentations/__init__.py
bioacoustics_augmentation/augmentations/mix.py
bioacoustics_augmentation/augmentations/classical/__init__.py
bioacoustics_augmentation/augmentations/classical/audio.py
bioacoustics_augmentation/augmentations/classical/spectrogram.py
bioacoustics_augmentation/utils/__init__.py
bioacoustics_augmentation/utils/audio.py
bioacoustics_augmentation/utils/image.py
bioacoustics_augmentation/utils/plot.py
bioacoustics_augmentation/utils/generator/__init__.py
bioacoustics_augmentation/utils/generator/guitar_chords.py
bioacoustics_augmentation-0.0.2.dist-info/licenses/LICENSE
bioacoustics_augmentation-0.0.2.dist-info/METADATA
bioacoustics_augmentation-0.0.2.dist-info/WHEEL
bioacoustics_augmentation-0.0.2.dist-info/entry_points.txt
bioacoustics_augmentation-0.0.2.dist-info/top_level.txt
bioacoustics_augmentation-0.0.2.dist-info/RECORD
